devenv/__init__.py
devenv/devenv.py
devenv/hadoop_build.py
devenv/local_network_bridge.py
devenv/presto_build.py
devenv/status.py
devenv/common/__init__.py
devenv/common/cluster.py
devenv/common/cluster_config.py
devenv/common/resources.py
devenv/common/timeout.py
images/Vagrantfile
images/__init__.py
images/boot2docker/Vagrantfile
images/boot2docker/.vagrant/machines/boot2docker/virtualbox/action_provision
images/boot2docker/.vagrant/machines/boot2docker/virtualbox/action_set_name
images/boot2docker/.vagrant/machines/boot2docker/virtualbox/creator_uid
images/boot2docker/.vagrant/machines/boot2docker/virtualbox/id
images/boot2docker/.vagrant/machines/boot2docker/virtualbox/index_uuid
images/boot2docker/.vagrant/machines/boot2docker/virtualbox/synced_folders
images/cdh5-base/Dockerfile
images/cdh5-base/README.md
images/cdh5-hive/Dockerfile
images/cdh5-hive/README.md
images/cdh5-hive/.vagrant/machines/default/docker/creator_uid
images/cdh5-hive/.vagrant/machines/default/docker/id
images/cdh5-hive/.vagrant/machines/default/docker/index_uuid
images/cdh5-hive/.vagrant/machines/default/docker/synced_folders
images/cdh5-hive/files/bootstrap.sh
images/cdh5-hive/files/setup.sh
images/cdh5-hive/files/startup.sh
images/cdh5-hive/files/supervisord.conf
images/cdh5-hive/files/conf/core-site.xml
images/cdh5-hive/files/conf/hadoop-env.sh
images/cdh5-hive/files/conf/hive-site.xml
images/cdh5-hive/files/conf/mapred-site.xml
images/cdh5-hive/files/conf/yarn-site.xml
images/cdh5-hive/files/supervisord.d/bootstrap.conf
images/cdh5-hive/files/supervisord.d/hdfs-datanode.conf
images/cdh5-hive/files/supervisord.d/hdfs-namenode.conf
images/cdh5-hive/files/supervisord.d/hive-metastore.conf
images/cdh5-hive/files/supervisord.d/hive-server2.conf
images/cdh5-hive/files/supervisord.d/mapreduce-historyserver.conf
images/cdh5-hive/files/supervisord.d/mysql-metastore.conf
images/cdh5-hive/files/supervisord.d/yarn-nodemanager.conf
presto_docker_devenv-0.2.dist-info/DESCRIPTION.rst
presto_docker_devenv-0.2.dist-info/METADATA
presto_docker_devenv-0.2.dist-info/RECORD
presto_docker_devenv-0.2.dist-info/WHEEL
presto_docker_devenv-0.2.dist-info/entry_points.txt
presto_docker_devenv-0.2.dist-info/metadata.json
presto_docker_devenv-0.2.dist-info/top_level.txt
