Metadata-Version: 2.0
Name: presto-docker-devenv
Version: 0.2
Summary: Presto docker developer environment.
Home-page: https://github.com/kokosing/git-gifi
Author: Grzegorz Kokosinski
Author-email: grzegorz.kokosinski a) teradata.com
License: UNKNOWN
Keywords: presto docker developer environmnent
Platform: UNKNOWN
Requires-Dist: docker-py (>=1.7.0)
Requires-Dist: python-vagrant (>=0.5.11)
